{
  "provider": "local_rule_based_summary",
  "summary_text": "APP / ma-3-15 回测显示总收益 1055.9492%，年化 None%，最大回撤 74.8409%，胜率 34.0%。 对比结果中 Sharpe 最优配置为 ma-3-15 (1.124117)。 敏感性分析提示 moving_average_crossover 参数敏感性中最佳为 ma-3-15（总收益 1055.9492%），最弱为 ma-8-21（总收益 562.1162%）。。",
  "key_metrics": {
    "total_return_pct": 1055.9492,
    "annualized_return_pct": null,
    "max_drawdown_pct": 74.8409,
    "win_rate_pct": 34.0,
    "sharpe_ratio": 1.124117,
    "sortino_ratio": 1.448755
  },
  "sensitivity_highlights": {
    "headline": "moving_average_crossover 参数敏感性中最佳为 ma-3-15（总收益 1055.9492%），最弱为 ma-8-21（总收益 562.1162%）。",
    "best_total_return": {
      "symbol": "APP",
      "strategy_family": "moving_average_crossover",
      "strategy_label": "ma-3-15",
      "strategy_text": "3日均线上穿15日均线买入，下穿卖出",
      "parameters": {
        "fast_period": 3,
        "slow_period": 15,
        "fast_type": "simple",
        "slow_type": "simple"
      },
      "metadata": {
        "symbol": "APP",
        "strategy_label": "ma-3-15",
        "strategy_version": "v1",
        "parse_version": "v1",
        "engine_version": "v1",
        "run_tag": "p2-20260412T075434Z",
        "benchmark_symbol": "AMD",
        "generated_at": "2026-04-12T07:54:35.326777+00:00"
      },
      "metrics": {
        "initial_capital": 100000.0,
        "final_equity": 1155949.17618,
        "total_return_pct": 1055.9492,
        "annualized_return_pct": null,
        "benchmark_return_pct": 532.9448,
        "excess_return_vs_benchmark_pct": 523.0044,
        "buy_and_hold_return_pct": 532.9448,
        "excess_return_vs_buy_and_hold_pct": 523.0044,
        "trade_count": 50,
        "entry_signal_count": 50,
        "win_count": 17,
        "loss_count": 33,
        "win_rate_pct": 34.0,
        "avg_trade_return_pct": 8.8298,
        "max_drawdown_pct": 74.8409,
        "avg_holding_days": 13.92,
        "avg_holding_bars": 13.92,
        "avg_holding_calendar_days": 20.04,
        "bars_used": 1249,
        "lookback_bars": 1249,
        "period_start": "2021-04-15T00:00:00",
        "period_end": "2026-04-06T00:00:00"
      },
      "compare_kpis": {
        "volatility_pct": 58.318009,
        "sortino_ratio": 1.448755,
        "calmar_ratio": null,
        "alpha_pct": 58.986701,
        "beta": 0.187729,
        "sharpe_ratio": 1.124117,
        "max_drawdown_pct": 74.8409,
        "win_rate_pct": 34.0,
        "avg_holding_period_days": 20.04,
        "profit_loss_ratio": 5.885216
      },
      "benchmark_summary": {
        "label": "当前标的买入并持有",
        "code": null,
        "method": "same_symbol_buy_and_hold",
        "requested_mode": "same_symbol_buy_and_hold",
        "resolved_mode": "same_symbol_buy_and_hold",
        "normalized_base": 1.0,
        "price_basis": "close",
        "start_date": "2021-04-15T00:00:00",
        "end_date": "2026-04-06T00:00:00",
        "start_price": 65.199997,
        "end_price": 412.679993,
        "return_pct": 532.9448,
        "auto_resolved": false,
        "fallback_used": false,
        "unavailable_reason": null
      },
      "buy_and_hold_summary": {
        "label": "当前标的买入并持有",
        "code": null,
        "method": "same_symbol_buy_and_hold",
        "requested_mode": "same_symbol_buy_and_hold",
        "resolved_mode": "same_symbol_buy_and_hold",
        "normalized_base": 1.0,
        "price_basis": "close",
        "start_date": "2021-04-15T00:00:00",
        "end_date": "2026-04-06T00:00:00",
        "start_price": 65.199997,
        "end_price": 412.679993,
        "return_pct": 532.9448,
        "auto_resolved": false,
        "fallback_used": false,
        "unavailable_reason": null
      },
      "warnings": [
        {
          "code": "default_fast_ma_type",
          "message": "未显式写出快线类型，当前默认使用 SMA。",
          "suggestion": "如需指数均线，可写成 EMA5。"
        },
        {
          "code": "default_slow_ma_type",
          "message": "未显式写出慢线类型，当前默认使用 SMA。",
          "suggestion": "如需指数均线，可写成 EMA20。"
        }
      ],
      "no_result_reason": null,
      "no_result_message": null
    },
    "worst_total_return": {
      "symbol": "APP",
      "strategy_family": "moving_average_crossover",
      "strategy_label": "ma-8-21",
      "strategy_text": "8日均线上穿21日均线买入，下穿卖出",
      "parameters": {
        "fast_period": 8,
        "slow_period": 21,
        "fast_type": "simple",
        "slow_type": "simple"
      },
      "metadata": {
        "symbol": "APP",
        "strategy_label": "ma-8-21",
        "strategy_version": "v1",
        "parse_version": "v1",
        "engine_version": "v1",
        "run_tag": "p2-20260412T075434Z",
        "benchmark_symbol": "AMD",
        "generated_at": "2026-04-12T07:54:35.605558+00:00"
      },
      "metrics": {
        "initial_capital": 100000.0,
        "final_equity": 662116.195263,
        "total_return_pct": 562.1162,
        "annualized_return_pct": null,
        "benchmark_return_pct": 532.9448,
        "excess_return_vs_benchmark_pct": 29.1714,
        "buy_and_hold_return_pct": 532.9448,
        "excess_return_vs_buy_and_hold_pct": 29.1714,
        "trade_count": 31,
        "entry_signal_count": 31,
        "win_count": 12,
        "loss_count": 19,
        "win_rate_pct": 38.7097,
        "avg_trade_return_pct": 13.3863,
        "max_drawdown_pct": 70.5328,
        "avg_holding_days": 22.4839,
        "avg_holding_bars": 22.4839,
        "avg_holding_calendar_days": 32.4839,
        "bars_used": 1249,
        "lookback_bars": 1249,
        "period_start": "2021-04-15T00:00:00",
        "period_end": "2026-04-06T00:00:00"
      },
      "compare_kpis": {
        "volatility_pct": 59.811378,
        "sortino_ratio": 1.163232,
        "calmar_ratio": null,
        "alpha_pct": 47.825399,
        "beta": 0.210348,
        "sharpe_ratio": 0.922676,
        "max_drawdown_pct": 70.5328,
        "win_rate_pct": 38.7097,
        "avg_holding_period_days": 32.4839,
        "profit_loss_ratio": 4.814553
      },
      "benchmark_summary": {
        "label": "当前标的买入并持有",
        "code": null,
        "method": "same_symbol_buy_and_hold",
        "requested_mode": "same_symbol_buy_and_hold",
        "resolved_mode": "same_symbol_buy_and_hold",
        "normalized_base": 1.0,
        "price_basis": "close",
        "start_date": "2021-04-15T00:00:00",
        "end_date": "2026-04-06T00:00:00",
        "start_price": 65.199997,
        "end_price": 412.679993,
        "return_pct": 532.9448,
        "auto_resolved": false,
        "fallback_used": false,
        "unavailable_reason": null
      },
      "buy_and_hold_summary": {
        "label": "当前标的买入并持有",
        "code": null,
        "method": "same_symbol_buy_and_hold",
        "requested_mode": "same_symbol_buy_and_hold",
        "resolved_mode": "same_symbol_buy_and_hold",
        "normalized_base": 1.0,
        "price_basis": "close",
        "start_date": "2021-04-15T00:00:00",
        "end_date": "2026-04-06T00:00:00",
        "start_price": 65.199997,
        "end_price": 412.679993,
        "return_pct": 532.9448,
        "auto_resolved": false,
        "fallback_used": false,
        "unavailable_reason": null
      },
      "warnings": [
        {
          "code": "default_fast_ma_type",
          "message": "未显式写出快线类型，当前默认使用 SMA。",
          "suggestion": "如需指数均线，可写成 EMA5。"
        },
        {
          "code": "default_slow_ma_type",
          "message": "未显式写出慢线类型，当前默认使用 SMA。",
          "suggestion": "如需指数均线，可写成 EMA20。"
        }
      ],
      "no_result_reason": null,
      "no_result_message": null
    }
  },
  "compare_highlights": {
    "best_total_return": {
      "symbol": "APP",
      "strategy_family": "moving_average_crossover",
      "strategy_label": "ma-3-15",
      "parameters": {
        "fast_period": 3,
        "slow_period": 15,
        "fast_type": "simple",
        "slow_type": "simple"
      },
      "metrics": {
        "initial_capital": 100000.0,
        "final_equity": 1155949.17618,
        "total_return_pct": 1055.9492,
        "annualized_return_pct": null,
        "benchmark_return_pct": 532.9448,
        "excess_return_vs_benchmark_pct": 523.0044,
        "buy_and_hold_return_pct": 532.9448,
        "excess_return_vs_buy_and_hold_pct": 523.0044,
        "trade_count": 50,
        "entry_signal_count": 50,
        "win_count": 17,
        "loss_count": 33,
        "win_rate_pct": 34.0,
        "avg_trade_return_pct": 8.8298,
        "max_drawdown_pct": 74.8409,
        "avg_holding_days": 13.92,
        "avg_holding_bars": 13.92,
        "avg_holding_calendar_days": 20.04,
        "bars_used": 1249,
        "lookback_bars": 1249,
        "period_start": "2021-04-15T00:00:00",
        "period_end": "2026-04-06T00:00:00"
      },
      "kpis": {
        "volatility_pct": 58.318009,
        "sortino_ratio": 1.448755,
        "calmar_ratio": null,
        "alpha_pct": 58.986701,
        "beta": 0.187729,
        "sharpe_ratio": 1.124117,
        "max_drawdown_pct": 74.8409,
        "win_rate_pct": 34.0,
        "avg_holding_period_days": 20.04,
        "profit_loss_ratio": 5.885216
      },
      "metadata": {
        "symbol": "APP",
        "strategy_label": "ma-3-15",
        "strategy_version": "v1",
        "parse_version": "v1",
        "engine_version": "v1",
        "run_tag": "p2-20260412T075434Z",
        "benchmark_symbol": "AMD",
        "generated_at": "2026-04-12T07:54:35.326777+00:00"
      }
    },
    "best_sharpe": {
      "symbol": "APP",
      "strategy_family": "moving_average_crossover",
      "strategy_label": "ma-3-15",
      "parameters": {
        "fast_period": 3,
        "slow_period": 15,
        "fast_type": "simple",
        "slow_type": "simple"
      },
      "metrics": {
        "initial_capital": 100000.0,
        "final_equity": 1155949.17618,
        "total_return_pct": 1055.9492,
        "annualized_return_pct": null,
        "benchmark_return_pct": 532.9448,
        "excess_return_vs_benchmark_pct": 523.0044,
        "buy_and_hold_return_pct": 532.9448,
        "excess_return_vs_buy_and_hold_pct": 523.0044,
        "trade_count": 50,
        "entry_signal_count": 50,
        "win_count": 17,
        "loss_count": 33,
        "win_rate_pct": 34.0,
        "avg_trade_return_pct": 8.8298,
        "max_drawdown_pct": 74.8409,
        "avg_holding_days": 13.92,
        "avg_holding_bars": 13.92,
        "avg_holding_calendar_days": 20.04,
        "bars_used": 1249,
        "lookback_bars": 1249,
        "period_start": "2021-04-15T00:00:00",
        "period_end": "2026-04-06T00:00:00"
      },
      "kpis": {
        "volatility_pct": 58.318009,
        "sortino_ratio": 1.448755,
        "calmar_ratio": null,
        "alpha_pct": 58.986701,
        "beta": 0.187729,
        "sharpe_ratio": 1.124117,
        "max_drawdown_pct": 74.8409,
        "win_rate_pct": 34.0,
        "avg_holding_period_days": 20.04,
        "profit_loss_ratio": 5.885216
      },
      "metadata": {
        "symbol": "APP",
        "strategy_label": "ma-3-15",
        "strategy_version": "v1",
        "parse_version": "v1",
        "engine_version": "v1",
        "run_tag": "p2-20260412T075434Z",
        "benchmark_symbol": "AMD",
        "generated_at": "2026-04-12T07:54:35.326777+00:00"
      }
    },
    "best_sortino": {
      "symbol": "APP",
      "strategy_family": "moving_average_crossover",
      "strategy_label": "ma-3-15",
      "parameters": {
        "fast_period": 3,
        "slow_period": 15,
        "fast_type": "simple",
        "slow_type": "simple"
      },
      "metrics": {
        "initial_capital": 100000.0,
        "final_equity": 1155949.17618,
        "total_return_pct": 1055.9492,
        "annualized_return_pct": null,
        "benchmark_return_pct": 532.9448,
        "excess_return_vs_benchmark_pct": 523.0044,
        "buy_and_hold_return_pct": 532.9448,
        "excess_return_vs_buy_and_hold_pct": 523.0044,
        "trade_count": 50,
        "entry_signal_count": 50,
        "win_count": 17,
        "loss_count": 33,
        "win_rate_pct": 34.0,
        "avg_trade_return_pct": 8.8298,
        "max_drawdown_pct": 74.8409,
        "avg_holding_days": 13.92,
        "avg_holding_bars": 13.92,
        "avg_holding_calendar_days": 20.04,
        "bars_used": 1249,
        "lookback_bars": 1249,
        "period_start": "2021-04-15T00:00:00",
        "period_end": "2026-04-06T00:00:00"
      },
      "kpis": {
        "volatility_pct": 58.318009,
        "sortino_ratio": 1.448755,
        "calmar_ratio": null,
        "alpha_pct": 58.986701,
        "beta": 0.187729,
        "sharpe_ratio": 1.124117,
        "max_drawdown_pct": 74.8409,
        "win_rate_pct": 34.0,
        "avg_holding_period_days": 20.04,
        "profit_loss_ratio": 5.885216
      },
      "metadata": {
        "symbol": "APP",
        "strategy_label": "ma-3-15",
        "strategy_version": "v1",
        "parse_version": "v1",
        "engine_version": "v1",
        "run_tag": "p2-20260412T075434Z",
        "benchmark_symbol": "AMD",
        "generated_at": "2026-04-12T07:54:35.326777+00:00"
      }
    }
  }
}