{
  "symbol": "AMD",
  "strategy_family": "macd_crossover",
  "strategy_label": "macd-baseline",
  "strategy_text": "MACD(12,26,9) 金叉买入，死叉卖出",
  "parameters": {
    "fast_period": 12,
    "slow_period": 26,
    "signal_period": 9
  },
  "metadata": {
    "symbol": "AMD",
    "strategy_label": "macd-baseline",
    "strategy_version": "v1",
    "parse_version": "v1",
    "engine_version": "v1",
    "run_tag": "p2-20260412T075434Z",
    "benchmark_symbol": "AMD",
    "generated_at": "2026-04-12T07:54:37.955822+00:00"
  },
  "metrics": {
    "initial_capital": 100000.0,
    "final_equity": 1244419.714563,
    "total_return_pct": 1144.4197,
    "annualized_return_pct": null,
    "benchmark_return_pct": 7763.5713,
    "excess_return_vs_benchmark_pct": -6619.1516,
    "buy_and_hold_return_pct": 7763.5713,
    "excess_return_vs_buy_and_hold_pct": -6619.1516,
    "trade_count": 100,
    "entry_signal_count": 100,
    "win_count": 41,
    "loss_count": 59,
    "win_rate_pct": 41.0,
    "avg_trade_return_pct": 3.5414,
    "max_drawdown_pct": 55.0948,
    "avg_holding_days": 12.91,
    "avg_holding_bars": 12.91,
    "avg_holding_calendar_days": 18.76,
    "bars_used": 2514,
    "lookback_bars": 2514,
    "period_start": "2016-04-06T00:00:00",
    "period_end": "2026-04-06T00:00:00"
  },
  "compare_kpis": {
    "volatility_pct": 41.022751,
    "sortino_ratio": 0.924386,
    "calmar_ratio": null,
    "alpha_pct": 3.971357,
    "beta": 0.490236,
    "sharpe_ratio": 0.820386,
    "max_drawdown_pct": 55.0948,
    "win_rate_pct": 41.0,
    "avg_holding_period_days": 18.76,
    "profit_loss_ratio": 2.942888
  },
  "benchmark_summary": {
    "label": "当前标的买入并持有",
    "code": null,
    "method": "same_symbol_buy_and_hold",
    "requested_mode": "same_symbol_buy_and_hold",
    "resolved_mode": "same_symbol_buy_and_hold",
    "normalized_base": 1.0,
    "price_basis": "close",
    "start_date": "2016-04-06T00:00:00",
    "end_date": "2026-04-06T00:00:00",
    "start_price": 2.8,
    "end_price": 220.179993,
    "return_pct": 7763.5713,
    "auto_resolved": false,
    "fallback_used": false,
    "unavailable_reason": null
  },
  "buy_and_hold_summary": {
    "label": "当前标的买入并持有",
    "code": null,
    "method": "same_symbol_buy_and_hold",
    "requested_mode": "same_symbol_buy_and_hold",
    "resolved_mode": "same_symbol_buy_and_hold",
    "normalized_base": 1.0,
    "price_basis": "close",
    "start_date": "2016-04-06T00:00:00",
    "end_date": "2026-04-06T00:00:00",
    "start_price": 2.8,
    "end_price": 220.179993,
    "return_pct": 7763.5713,
    "auto_resolved": false,
    "fallback_used": false,
    "unavailable_reason": null
  },
  "warnings": [],
  "no_result_reason": null,
  "no_result_message": null
}